{"cameraMode":{"drawMode":0,"name":"Shaded","section":"Shading Mode"},"sceneLighting":false,"audioPlay":false,"sceneViewState":{"m_AlwaysRefresh":false,"showFog":true,"showSkybox":false,"showFlares":true,"showImageEffects":true,"showParticleSystems":true,"showVisualEffectGraphs":true,"m_FxEnabled":true},"in2DMode":false,"pivot":{"x":-5.851642608642578,"y":-1.2398691177368165,"z":-1.8599319458007813},"rotation":{"x":-0.08350103348493576,"y":0.8651400804519653,"z":-0.15368695557117463,"w":-0.4700464606285095},"size":10.26766300201416,"orthographic":false}